{
  "flight_key": "313",
  "split": "val",
  "generated_at": "2026-02-07T13:25:19.313891",
  "frame_count": 0,
  "flight_info": {
    "sharepoint_link": "https://fhooe.sharepoint.com/teams/BAMBI-dev/Freigegebene%20Dokumente/Processed/FH/2024_10_21_Stm_Feldbach_Straden/1581F62HD226U00B7033_M30T/004_S1R187",
    "key": "313",
    "weather": null,
    "start_time": "2024-10-21T12:04:15",
    "end_time": "2024-10-21T12:21:55",
    "drone_name": "Matric 30 Thermal",
    "drone_instance_id": 1
  },
  "species_present": {}
}